MStudio/__init__.py
MStudio/app.py
MStudio/main.py
MStudio/core/__init__.py
MStudio/core/animation_controller.py
MStudio/core/data_manager.py
MStudio/core/marker_visual_settings.py
MStudio/core/outlier_detector.py
MStudio/core/state_manager.py
MStudio/gui/TRCviewerWidgets.py
MStudio/gui/__init__.py
MStudio/gui/customization_toolbar.py
MStudio/gui/editWindow.py
MStudio/gui/filterUI.py
MStudio/gui/markerPlot.py
MStudio/gui/markerPlotUI.py
MStudio/gui/plotCreator.py
MStudio/gui/opengl/GLMarkerRenderer.py
MStudio/gui/opengl/GLPlotCreator.py
MStudio/gui/opengl/GridUtils.py
MStudio/gui/opengl/__init__.py
MStudio/utils/__init__.py
MStudio/utils/analysisMode.py
MStudio/utils/dataLoader.py
MStudio/utils/dataProcessor.py
MStudio/utils/dataSaver.py
MStudio/utils/filtering.py
MStudio/utils/mouseHandler.py
MStudio/utils/performance_utils.py
MStudio/utils/skeletons.py
MStudio/utils/viewReset.py
MStudio/utils/viewToggles.py
mstudio-0.1.5.dist-info/licenses/LICENSE
mstudio-0.1.5.dist-info/METADATA
mstudio-0.1.5.dist-info/WHEEL
mstudio-0.1.5.dist-info/entry_points.txt
mstudio-0.1.5.dist-info/top_level.txt
mstudio-0.1.5.dist-info/RECORD
