Metadata-Version: 2.4
Name: MStudio
Version: 0.1.5
Summary: A motion capture marker data visualization and editing tool
Author-email: HunMin Kim <hunminkim98@gmail.com>
License: MIT License
Project-URL: Homepage, https://github.com/hunminkim98/MStudio
Project-URL: Bug Tracker, https://github.com/hunminkim98/MStudio/issues
Keywords: biomechanics,kinemaics,marker,editor,Pose2Sim,Sports2D,mocap,motion capture,human pose
Classifier: Programming Language :: Python :: 3
Classifier: Development Status :: 2 - Pre-Alpha
Classifier: Intended Audience :: Science/Research
Classifier: Intended Audience :: Healthcare Industry
Classifier: Operating System :: OS Independent
License-File: LICENSE
Requires-Dist: customtkinter
Requires-Dist: matplotlib
Requires-Dist: pyopengl
Requires-Dist: pyopengl-accelerate
Requires-Dist: pyopengltk
Requires-Dist: numpy>=1.19
Requires-Dist: pandas>=1.5
Requires-Dist: c3d
Requires-Dist: anytree
Requires-Dist: filterpy
Requires-Dist: scipy
Requires-Dist: statsmodels
Requires-Dist: opencv-python
Dynamic: license-file
